{"config": {"preseeding": true, "preseeding-minimal": false, "preseeding-grow": true, "preseeding-grow-maxsat": false, "sat-polarity": true, "postpone_opt": true, "postpone_opt_incr": false, "postpone_opt_greedy": true, "grow": true, "grow_sat": false, "grow_subset_maximal": false, "grow_maxsat": true, "timeout": 14400, "instance": "frietkot", "output": "results/rq1_4/20201218/20201218181606177881.json"}, "results": {"HS": [1, 2, 1, 1, 1], "HS_greedy": [0, 18, 0, 0, 0], "HS_incr": [0, 0, 0, 0, 0], "HS-opt-time": [0.0006589889526367188, 0.0016238689422607422, 0.0007412433624267578, 0.0010259151458740234, 0.0008516311645507812], "HS-postpone-time": [0, 0.004976749420166016, 0, 0, 0], "SAT-time": [6.031990051269531e-05, 0.0029230117797851562, 7.343292236328125e-05, 8.630752563476562e-05, 8.749961853027344e-05], "grow-time": [0, 0.03999924659729004, 0, 0, 0], "#expl": 5, "expl_seq": [{"constraints": [902], "derived": [-895]}, {"constraints": [905, -895], "derived": [-891]}, {"constraints": [896, -891], "derived": [892]}, {"constraints": [900, 892, 901], "derived": [894]}, {"constraints": [-891, 894, 903], "derived": [-893]}], "OUS-time": [0.0008928775787353516, 0.05263495445251465, 0.0009508132934570312, 0.0013110637664794922, 0.0011146068572998047], "timeout": false}}