{"config": {"preseeding": true, "preseeding-minimal": true, "preseeding-grow": false, "preseeding-grow-maxsat": false, "sat-polarity": true, "postpone_opt": true, "postpone_opt_incr": true, "postpone_opt_greedy": true, "grow": true, "grow_sat": false, "grow_subset_maximal": false, "grow_maxsat": true, "timeout": 14400, "instance": "frietkot", "output": "results/rq1_4/20201218/20201218164820704380.json"}, "results": {"HS": [2, 1, 1, 1], "HS_greedy": [13, 0, 0, 0], "HS_incr": [19, 0, 0, 0], "HS-opt-time": [0.0022330284118652344, 0.0019140243530273438, 0.0018181800842285156, 0.0012693405151367188], "HS-postpone-time": [0.003222942352294922, 0, 0, 0], "SAT-time": [0.0023183822631835938, 0.00012350082397460938, 8.320808410644531e-05, 5.435943603515625e-05], "grow-time": [0.026541709899902344, 0, 0, 0], "#expl": 4, "expl_seq": [{"constraints": [82, 85], "derived": [-71, -75]}, {"constraints": [-71, 76], "derived": [72]}, {"constraints": [80, 81, 72], "derived": [74]}, {"constraints": [-71, 74, 83], "derived": [-73]}], "OUS-time": [0.03829050064086914, 0.002323150634765625, 0.0022974014282226562, 0.0014424324035644531], "timeout": false}}