{"config": {"preseeding": true, "preseeding-minimal": true, "preseeding-grow": false, "preseeding-grow-maxsat": false, "sat-polarity": true, "postpone_opt": true, "postpone_opt_incr": true, "postpone_opt_greedy": false, "grow": false, "grow_sat": false, "grow_subset_maximal": false, "grow_maxsat": false, "timeout": 14400, "instance": "simple", "output": "results/rq1_4/20201218/20201218192108499715.json"}, "results": {"HS": [3, 7, 1], "HS_greedy": [0, 0, 0], "HS_incr": [6, 12, 0], "HS-opt-time": [0.002292156219482422, 0.005698680877685547, 0.0004456043243408203], "HS-postpone-time": [5.8650970458984375e-05, 0.00010848045349121094, 0], "SAT-time": [0.0001494884490966797, 0.00035452842712402344, 2.09808349609375e-05], "grow-time": [4.291534423828125e-06, 9.059906005859375e-06, 0], "#expl": 3, "expl_seq": [{"constraints": [4], "derived": [1]}, {"constraints": [1, 5, 7], "derived": [-3]}, {"constraints": [1, -3, 6], "derived": [2]}], "OUS-time": [0.0029251575469970703, 0.007018089294433594, 0.0005550384521484375], "timeout": false}}