{"config": {"preseeding": true, "preseeding-minimal": false, "preseeding-grow": true, "preseeding-grow-maxsat": false, "sat-polarity": true, "postpone_opt": true, "postpone_opt_incr": true, "postpone_opt_greedy": false, "grow": true, "grow_sat": false, "grow_subset_maximal": true, "grow_maxsat": false, "timeout": 14400, "instance": "simple", "output": "results/rq1_2/20201217/20201217151209021534.json"}, "results": {"HS": [1, 3, 1], "HS_greedy": [0, 0, 0], "HS_incr": [0, 2, 0], "HS-opt-time": [0.2818734645843506, 0.0018193721771240234, 0.0005707740783691406], "HS-postpone-time": [0, 1.71661376953125e-05, 0], "SAT-time": [3.814697265625e-05, 0.00017261505126953125, 2.5272369384765625e-05], "#expl": 3, "expl_seq": [{"constraints": [4], "derived": [1]}, {"constraints": [1, 5, 7], "derived": [-3]}, {"constraints": [1, -3, 6], "derived": [2]}], "OUS-time": [0.299091100692749, 0.055594444274902344, 0.0006899833679199219], "timeout": false}}