{"config": {"preseeding": false, "preseeding-minimal": false, "sat-polarity": false, "postpone_opt": false, "postpone_opt_incr": false, "postpone_opt_greedy": false, "subset_maximal": true, "timeout": 7200, "instance": "frietkot"}, "results": {"HS": [6, 4, 5, 12, 2], "HS_greedy": [0, 0, 0, 0, 0], "HS_incr": [0, 0, 0, 0, 0], "HS-opt-time": [0.0018277168273925781, 0.0016138553619384766, 0.004303693771362305, 0.015194892883300781, 0.0014681816101074219], "HS-postpone-time": [0, 0, 0, 0, 0], "SAT-time": [0.0002536773681640625, 0.0001475811004638672, 0.00028204917907714844, 0.0005674362182617188, 0.00010013580322265625], "#expl": 5, "expl_seq": [{"constraints": [12], "derived": [-5]}, {"constraints": [-5, 15], "derived": [-1]}, {"constraints": [6, -1], "derived": [2]}, {"constraints": [11, 2, 10], "derived": [4]}, {"constraints": [4, 13, -1], "derived": [-3]}], "OUS-time": [0.07038092613220215, 0.0032274723052978516, 0.05872774124145508, 0.10059809684753418, 0.014115095138549805]}}