{"config": {"preseeding": true, "preseeding-minimal": true, "preseeding-grow": false, "preseeding-grow-maxsat": false, "sat-polarity": true, "postpone_opt": true, "postpone_opt_incr": true, "postpone_opt_greedy": true, "grow": false, "grow_sat": false, "grow_subset_maximal": false, "grow_maxsat": false, "timeout": 14400, "instance": "origin-problem", "output": "results/rq1_4/20201217/20201217225327829721.json"}, "results": {"HS": [1], "HS_greedy": [2163], "HS_incr": [62916], "HS-opt-time": [0.023238658905029297], "HS-postpone-time": [13894.204982995987], "SAT-time": [279.741646528244], "#expl": 0, "expl_seq": [], "OUS-time": [14399.285709619522], "timeout": true}}