{"config": {"preseeding": true, "preseeding-minimal": true, "preseeding-grow": false, "preseeding-grow-maxsat": false, "sat-polarity": true, "postpone_opt": true, "postpone_opt_incr": true, "postpone_opt_greedy": true, "grow": true, "grow_sat": false, "grow_subset_maximal": false, "grow_maxsat": true, "timeout": 14400, "instance": "frietkot", "output": "results/rq1_4/20201218/20201218192108499460.json"}, "results": {"HS": [1, 2, 1, 1, 1], "HS_greedy": [0, 8, 0, 0, 0], "HS_incr": [0, 25, 0, 0, 0], "HS-opt-time": [0.0008709430694580078, 0.0021123886108398438, 0.0009801387786865234, 0.0009539127349853516, 0.0009505748748779297], "HS-postpone-time": [0, 0.0010247230529785156, 0, 0, 0], "SAT-time": [1.9550323486328125e-05, 0.0007326602935791016, 2.5033950805664062e-05, 2.5272369384765625e-05, 2.6464462280273438e-05], "grow-time": [0, 0.014679431915283203, 0, 0, 0], "#expl": 5, "expl_seq": [{"constraints": [12], "derived": [-5]}, {"constraints": [-5, 15], "derived": [-1]}, {"constraints": [6, -1], "derived": [2]}, {"constraints": [11, 2, 10], "derived": [4]}, {"constraints": [4, 13, -1], "derived": [-3]}], "OUS-time": [0.0010788440704345703, 0.01985907554626465, 0.001157999038696289, 0.0011076927185058594, 0.0011076927185058594], "timeout": false}}