{"config": {"preseeding": true, "preseeding-minimal": false, "preseeding-grow": true, "preseeding-grow-maxsat": false, "sat-polarity": true, "postpone_opt": false, "postpone_opt_incr": false, "postpone_opt_greedy": false, "grow": true, "grow_sat": false, "grow_subset_maximal": false, "grow_maxsat": true, "timeout": 14400, "instance": "frietkot", "output": "results/rq1_4/20201218/20201218164507713548.json"}, "results": {"HS": [3, 2, 1, 3, 2], "HS_greedy": [0, 0, 0, 0, 0], "HS_incr": [0, 0, 0, 0, 0], "HS-opt-time": [0.023673534393310547, 0.002919912338256836, 0.0010218620300292969, 0.003720521926879883, 0.0012202262878417969], "HS-postpone-time": [0, 0, 0, 0, 0], "SAT-time": [0.0002448558807373047, 0.0002372264862060547, 0.0001888275146484375, 0.0004687309265136719, 0.00022935867309570312], "grow-time": [0.0023784637451171875, 0.018145322799682617, 0, 0.04453587532043457, 0.0007996559143066406], "#expl": 5, "expl_seq": [{"constraints": [12], "derived": [-5]}, {"constraints": [-5, 15], "derived": [-1]}, {"constraints": [6, -1], "derived": [2]}, {"constraints": [11, 2, 10], "derived": [4]}, {"constraints": [4, 13, -1], "derived": [-3]}], "OUS-time": [0.026784658432006836, 0.021860599517822266, 0.0015523433685302734, 0.049552202224731445, 0.002683877944946289], "timeout": false}}