{"config": {"preseeding": true, "preseeding-minimal": true, "preseeding-grow": false, "preseeding-grow-maxsat": false, "sat-polarity": true, "postpone_opt": true, "postpone_opt_incr": true, "postpone_opt_greedy": true, "grow": true, "grow_sat": false, "grow_subset_maximal": false, "grow_maxsat": true, "timeout": 14400, "instance": "frietkot", "output": "results/rq1_4/20201218/20201218180657777831.json"}, "results": {"HS": [1, 2, 1, 1, 1], "HS_greedy": [0, 9, 0, 0, 0], "HS_incr": [0, 17, 0, 0, 0], "HS-opt-time": [0.0004830360412597656, 0.0017642974853515625, 0.0006883144378662109, 0.0009098052978515625, 0.0008871555328369141], "HS-postpone-time": [0, 0.0018222332000732422, 0, 0, 0], "SAT-time": [3.170967102050781e-05, 0.0008404254913330078, 6.103515625e-05, 8.535385131835938e-05, 5.53131103515625e-05], "grow-time": [0, 0.011353015899658203, 0, 0, 0], "#expl": 5, "expl_seq": [{"constraints": [57], "derived": [-50]}, {"constraints": [57, 60], "derived": [-46]}, {"constraints": [-46, 51, -50], "derived": [47]}, {"constraints": [56, 55, 47], "derived": [49]}, {"constraints": [-50, 47, 49, -46, 58], "derived": [-48]}], "OUS-time": [0.0006201267242431641, 0.0177614688873291, 0.0008745193481445312, 0.0011594295501708984, 0.001081705093383789], "timeout": false}}