{"config": {"preseeding": true, "preseeding-minimal": true, "preseeding-grow": false, "preseeding-grow-maxsat": false, "sat-polarity": true, "postpone_opt": true, "postpone_opt_incr": true, "postpone_opt_greedy": true, "grow": true, "grow_sat": false, "grow_subset_maximal": false, "grow_maxsat": true, "timeout": 14400, "instance": "frietkot", "output": "results/rq1_4/20201218/20201218163903017037.json"}, "results": {"HS": [1, 2, 1, 1, 1], "HS_greedy": [0, 10, 0, 0, 0], "HS_incr": [0, 20, 0, 0, 0], "HS-opt-time": [0.0009622573852539062, 0.0566713809967041, 0.0018131732940673828, 0.001657247543334961, 0.002277851104736328], "HS-postpone-time": [0, 0.0044858455657958984, 0, 0, 0], "SAT-time": [0.00010251998901367188, 0.002392292022705078, 8.940696716308594e-05, 7.82012939453125e-05, 9.465217590332031e-05], "grow-time": [0, 0.15092062950134277, 0, 0, 0], "#expl": 5, "expl_seq": [{"constraints": [12], "derived": [-5]}, {"constraints": [12, 15], "derived": [-1]}, {"constraints": [6, -1], "derived": [2]}, {"constraints": [11, 2, 10], "derived": [4]}, {"constraints": [4, 13, -1], "derived": [-3]}], "OUS-time": [0.0014660358428955078, 0.21845102310180664, 0.0021469593048095703, 0.0019021034240722656, 0.0025832653045654297], "timeout": false}}