{"config": {"preseeding": true, "preseeding-minimal": true, "preseeding-grow": false, "preseeding-grow-maxsat": false, "sat-polarity": true, "postpone_opt": true, "postpone_opt_incr": false, "postpone_opt_greedy": true, "grow": true, "grow_sat": false, "grow_subset_maximal": false, "grow_maxsat": true, "timeout": 14400, "instance": "simple", "output": "results/rq1_4/20201218/20201218163903017414.json"}, "results": {"HS": [3, 1, 1], "HS_greedy": [6, 0, 0], "HS_incr": [0, 0, 0], "HS-opt-time": [0.02745532989501953, 0.0010428428649902344, 0.0009446144104003906], "HS-postpone-time": [0.0004248619079589844, 0, 0], "SAT-time": [0.0006501674652099609, 9.083747863769531e-05, 8.535385131835938e-05], "grow-time": [0.01356959342956543, 0, 0], "#expl": 3, "expl_seq": [{"constraints": [4, 6], "derived": [1]}, {"constraints": [1, 5, 6], "derived": [2]}, {"constraints": [1, 2, 7], "derived": [-3]}], "OUS-time": [0.04314136505126953, 0.0012867450714111328, 0.0011789798736572266], "timeout": false}}