{"config": {"preseeding": false, "sat-polarity": false, "sat-polarity-initial": true, "postpone_opt": false, "postpone_opt_incr": false, "postpone_opt_greedy": false, "grow": false, "grow_sat": false, "grow_subset_maximal": false, "grow_maxsat": false, "grow_maxsat_full_pos": false, "grow_maxsat_full_inv": false, "grow_maxsat_full_unif": false, "grow_maxsat_initial_pos": false, "grow_maxsat_initial_inv": false, "grow_maxsat_initial_unif": false, "grow_maxsat_actual_pos": false, "grow_maxsat_actual_unif": false, "grow_maxsat_actual_inv": false, "timeout": 7200, "instance": "origin-problem", "output": "/data/brussel/101/vsc10143/OUSResults/effectPreseeding/2021010818/20210108185449125900.json"}, "results": {"HS": [5551, 8], "HS_greedy": [0, 0], "HS_incr": [0, 0], "HS-opt-time": [7109.062224149704, 19.55635690689087], "HS-postpone-time": [0, 0], "SAT-time": [57.45542860031128, 0.0581512451171875], "grow-time": [0.022725582122802734, 2.4318695068359375e-05], "#expl": 1, "expl_seq": [{"constraints": [35539], "derived": [33857]}], "OUS-time": [7178.687659025192, 0], "timeout": true}}