{"config": {"preseeding": true, "preseeding-minimal": false, "preseeding-grow": false, "preseeding-grow-maxsat": true, "sat-polarity": true, "postpone_opt": true, "postpone_opt_incr": true, "postpone_opt_greedy": false, "grow": true, "grow_sat": false, "grow_subset_maximal": false, "grow_maxsat": true, "timeout": 14400, "instance": "simple", "output": "results/rq1_3/20201217/20201217205759172633.json"}, "results": {"HS": [2, 1, 1], "HS_greedy": [0, 0, 0], "HS_incr": [2, 0, 0], "HS-opt-time": [0.0019850730895996094, 0.00048470497131347656, 0.0003886222839355469], "HS-postpone-time": [1.0013580322265625e-05, 0, 0], "SAT-time": [8.511543273925781e-05, 2.3603439331054688e-05, 1.9073486328125e-05], "#expl": 3, "expl_seq": [{"constraints": [4], "derived": [1]}, {"constraints": [1, 5, 6], "derived": [2]}, {"constraints": [2, 7], "derived": [-3]}], "OUS-time": [0.0032486915588378906, 0.0005772113800048828, 0.00047087669372558594], "timeout": false}}