{"config": {"preseeding": true, "sat-polarity": true, "sat-polarity-initial": false, "postpone_opt": true, "postpone_opt_incr": false, "postpone_opt_greedy": true, "grow": true, "grow_sat": false, "grow_subset_maximal": false, "grow_maxsat": true, "maxsat_polarities": true, "grow_maxsat_full_pos": true, "grow_maxsat_full_inv": false, "grow_maxsat_full_unif": false, "grow_maxsat_initial_pos": false, "grow_maxsat_initial_inv": false, "grow_maxsat_initial_unif": false, "grow_maxsat_actual_pos": false, "grow_maxsat_actual_unif": false, "grow_maxsat_actual_inv": false, "timeout": 7200, "instance": "p13", "output": "/data/brussel/101/vsc10143/OUSResults/experiment4/2021011308/20210113081933869812.json"}, "results": {"HS": [0, 14, 1], "HS_greedy": [0, 44, 39], "HS_incr": [0, 0, 0], "HS-opt-time": [0, 0.1316227912902832, 0.01999378204345703], "HS-postpone-time": [0, 0.03771710395812988, 0.03107738494873047], "SAT-time": [0.2533869743347168, 0.436542272567749, 0.36314868927001953], "grow-time": [43.679632902145386, 4228.499818086624, 2831.088490486145], "#expl": 1, "expl_seq": [{"constraints": [42702], "derived": [-41023, -41026]}], "OUS-time": [0, 4229.213703632355, 0], "timeout": true}}