{"config": {"preseeding": true, "preseeding-minimal": false, "preseeding-grow": true, "preseeding-grow-maxsat": false, "sat-polarity": true, "postpone_opt": false, "postpone_opt_incr": false, "postpone_opt_greedy": false, "grow": true, "grow_sat": false, "grow_subset_maximal": false, "grow_maxsat": true, "timeout": 3600, "instance": "frietkot", "output": "results/20201217/20201217154417584676.json"}, "results": {"HS": [1, 2, 3, 3, 2], "HS_greedy": [0, 0, 0, 0, 0], "HS_incr": [0, 0, 0, 0, 0], "HS-opt-time": [0.0008754730224609375, 0.001699209213256836, 0.002559661865234375, 0.0019273757934570312, 0.000606536865234375], "HS-postpone-time": [0, 0, 0, 0, 0], "SAT-time": [7.2479248046875e-05, 0.00015735626220703125, 0.0002930164337158203, 0.00018978118896484375, 8.249282836914062e-05], "#expl": 5, "expl_seq": [{"constraints": [15], "derived": [-8]}, {"constraints": [-8, 18], "derived": [-4]}, {"constraints": [9, -4], "derived": [5]}, {"constraints": [13, 5, 14], "derived": [7]}, {"constraints": [16, -4, 7], "derived": [-6]}], "OUS-time": [0.0011854171752929688, 0.0034999847412109375, 0.004786252975463867, 0.003815174102783203, 0.0013327598571777344], "timeout": false}}