{"config": {"preseeding": true, "sat-polarity": true, "sat-polarity-initial": true, "postpone_opt": true, "postpone_opt_incr": false, "postpone_opt_greedy": true, "grow": true, "grow_sat": false, "grow_subset_maximal": false, "grow_maxsat": true, "maxsat_polarities": true, "grow_maxsat_full_pos": false, "grow_maxsat_full_inv": true, "grow_maxsat_full_unif": false, "grow_maxsat_initial_pos": false, "grow_maxsat_initial_inv": false, "grow_maxsat_initial_unif": false, "grow_maxsat_actual_pos": false, "grow_maxsat_actual_unif": false, "grow_maxsat_actual_inv": false, "timeout": 7200, "instance": "p18", "output": "/data/brussel/101/vsc10143/OUSResults/experiment6_cous/2021011612/20210116124313538893.json"}, "results": {"HS": [0, 1], "HS_greedy": [0, 169], "HS_incr": [0, 0], "HS-opt-time": [0, 0.001329183578491211], "HS-postpone-time": [0, 0.5009324550628662], "SAT-time": [0.008632659912109375, 1.7707035541534424], "grow-time": [0.16324424743652344, 494.9898872375488], "#expl": 0, "expl_seq": [], "OUS-time": [0, 0], "timeout": true}}