{"config": {"preseeding": false, "sat-polarity": true, "sat-polarity-initial": false, "postpone_opt": true, "postpone_opt_incr": false, "postpone_opt_greedy": true, "grow": true, "grow_sat": false, "grow_subset_maximal": true, "grow_maxsat": false, "maxsat_polarities": true, "grow_maxsat_full_pos": false, "grow_maxsat_full_inv": false, "grow_maxsat_full_unif": false, "grow_maxsat_initial_pos": false, "grow_maxsat_initial_inv": false, "grow_maxsat_initial_unif": false, "grow_maxsat_actual_pos": false, "grow_maxsat_actual_unif": false, "grow_maxsat_actual_inv": false, "timeout": 7200, "instance": "p13", "output": "/data/brussel/101/vsc10143/OUSResults/experiment4/2021011308/20210113081933868673.json"}, "results": {"HS": [0, 29, 2, 1, 1, 55], "HS_greedy": [0, 195, 1610, 0, 0, 1402], "HS_incr": [0, 0, 0, 0, 0, 0], "HS-opt-time": [0, 14.075998544692993, 35.32402181625366, 27.819032669067383, 28.6020450592041, 6956.818567752838], "HS-postpone-time": [0, 0.6194779872894287, 45.91814947128296, 0, 0, 30.085039138793945], "SAT-time": [0, 1.0393767356872559, 8.996288299560547, 0.0007531642913818359, 0.002245187759399414, 8.215447902679443], "grow-time": [0, 0.7487533092498779, 5.929676055908203, 0, 0, 5.38384222984314], "#expl": 4, "expl_seq": [{"constraints": [1690], "derived": [-14, -11]}, {"constraints": [1696], "derived": [22]}, {"constraints": [22, 151], "derived": [-7, -12, -2, -17]}, {"constraints": [153, 22], "derived": [-24, -23, -21, -25]}], "OUS-time": [0, 16.210022449493408, 93.75154733657837, 27.822429656982422, 28.607107639312744, 0], "timeout": true}}