{"config": {"preseeding": true, "sat-polarity": true, "sat-polarity-initial": false, "postpone_opt": true, "postpone_opt_incr": true, "postpone_opt_greedy": false, "grow": true, "grow_sat": false, "grow_subset_maximal": true, "grow_maxsat": false, "maxsat_polarities": true, "grow_maxsat_full_pos": false, "grow_maxsat_full_inv": false, "grow_maxsat_full_unif": false, "grow_maxsat_initial_pos": false, "grow_maxsat_initial_inv": false, "grow_maxsat_initial_unif": false, "grow_maxsat_actual_pos": false, "grow_maxsat_actual_unif": false, "grow_maxsat_actual_inv": false, "timeout": 7200, "instance": "p19", "output": "/data/brussel/101/vsc10143/OUSResults/experiment4/2021011901/20210119014750539371.json"}, "results": {"HS": [0, 1, 100, 76], "HS_greedy": [0, 0, 0, 0], "HS_incr": [0, 0, 1133, 823], "HS-opt-time": [0, 0.010954618453979492, 620.0905914306641, 6356.96711230278], "HS-postpone-time": [0, 0, 0.06461548805236816, 0.05092811584472656], "SAT-time": [2.7187211513519287, 0.00012373924255371094, 60.06803894042969, 47.06629967689514], "grow-time": [2.0528340339660645, 0, 42.69853115081787, 32.93925762176514], "#expl": 2, "expl_seq": [{"constraints": [88289], "derived": [-88060, -88059, -88058, -88057, -88056, -88054, -88053, -88052, -88051, -88050, -88048, -88047, -88046, -88045, -88044, -88042, -88041, -88040, -88039, -88038, 88037, 88043, 88049, 88055, 88061], "cost": 60}, {"constraints": [92113], "derived": [-88134], "cost": 100}], "OUS-time": [0, 0.012737274169921875, 696.6670134067535, 0], "timeout": true}}