{"config": {"instance": "p18", "timeout": 14400}, "results": {"#expl": 116, "expl_seq": [{"constraints": [1687], "derived": [7], "cost": 100}, {"constraints": [151, 7], "derived": [-22, -12, -2, -17], "cost": 61}, {"constraints": [153, 7], "derived": [-8, -6, -10, -9], "cost": 61}, {"constraints": [1693], "derived": [66], "cost": 100}, {"constraints": [1693], "derived": [66], "cost": 100}, {"constraints": [1697, 178], "derived": [-150], "cost": 160}, {"constraints": [162, 66, 159], "derived": [-70, -69, -68, -67], "cost": 121}, {"constraints": [159, 66, 179, 7], "derived": [-131], "cost": 122}, {"constraints": [163, 1695], "derived": [-98], "cost": 160}, {"constraints": [59, 159], "derived": [-64, -54, -74], "cost": 61}, {"constraints": [59, 159], "derived": [-64, -54, -74], "cost": 61}, {"constraints": [59, 180, 7], "derived": [134], "cost": 62}, {"constraints": [59, 180, 7], "derived": [134], "cost": 62}, {"constraints": [59, 180, 7], "derived": [134], "cost": 62}, {"constraints": [59, 180, 7], "derived": [134], "cost": 62}, {"constraints": [59, 180, 7], "derived": [134], "cost": 62}, {"constraints": [59, 180, 7], "derived": [134], "cost": 62}, {"constraints": [59, 180, 7], "derived": [134], "cost": 62}, {"constraints": [59, 180, 7], "derived": [134], "cost": 62}, {"constraints": [1697, 178], "derived": [-150], "cost": 160}, {"constraints": [42, 155], "derived": [-32, -47, -37, -27], "cost": 61}, {"constraints": [42, 155], "derived": [-32, -47, -37, -27], "cost": 61}, {"constraints": [1697, 178], "derived": [-150], "cost": 160}, {"constraints": [1697, 178], "derived": [-150], "cost": 160}, {"constraints": [1697, 178], "derived": [-150], "cost": 160}, {"constraints": [1697, 178], "derived": [-150], "cost": 160}, {"constraints": [1697, 178], "derived": [-150], "cost": 160}, {"constraints": [1697, 178], "derived": [-150], "cost": 160}, {"constraints": [1697, 178], "derived": [-150], "cost": 160}, {"constraints": [1697, 178], "derived": [-150], "cost": 160}, {"constraints": [1697, 178], "derived": [-150], "cost": 160}, {"constraints": [81, 163], "derived": [-96], "cost": 61}, {"constraints": [1697, 178], "derived": [-150], "cost": 160}, {"constraints": [1697, 178], "derived": [-150], "cost": 160}, {"constraints": [1697, 178], "derived": [-150], "cost": 160}, {"constraints": [163, 1695], "derived": [-98], "cost": 160}, {"constraints": [163, 1695], "derived": [-98], "cost": 160}, {"constraints": [163, 1695], "derived": [-98], "cost": 160}, {"constraints": [159, 63], "derived": [-53, -73], "cost": 61}, {"constraints": [161, 63], "derived": [-62, -65], "cost": 61}, {"constraints": [1697, 178], "derived": [-150], "cost": 160}, {"constraints": [1697, 178], "derived": [-150], "cost": 160}, {"constraints": [1697, 178], "derived": [-150], "cost": 160}, {"constraints": [72, 161], "derived": [-75], "cost": 61}, {"constraints": [72, 159], "derived": [-52], "cost": 61}, {"constraints": [159, 66, 162, 72, 59, 63], "derived": [55], "cost": 124}, {"constraints": [159, 66, 162, 72, 59, 63], "derived": [55], "cost": 124}, {"constraints": [159, 66, 162, 72, 59, 63], "derived": [55], "cost": 124}, {"constraints": [159, 66, 162, 72, 59, 63], "derived": [55], "cost": 124}, {"constraints": [159, 66, 162, 72, 59, 63], "derived": [55], "cost": 124}, {"constraints": [159, 66, 162, 72, 59, 63], "derived": [55], "cost": 124}, {"constraints": [163, 1695], "derived": [-98], "cost": 160}, {"constraints": [163, 1695], "derived": [-98], "cost": 160}, {"constraints": [163, 1695], "derived": [-98], "cost": 160}, {"constraints": [177, 42, 19], "derived": [117], "cost": 62}, {"constraints": [177, 42, 19], "derived": [117], "cost": 62}, {"constraints": [177, 42, 19], "derived": [117], "cost": 62}, {"constraints": [177, 42, 19], "derived": [117], "cost": 62}, {"constraints": [81, 186, -146], "derived": [-122], "cost": 62}, {"constraints": [81, 186, -146], "derived": [-122], "cost": 62}, {"constraints": [177, 42, 19], "derived": [117], "cost": 62}, {"constraints": [177, 42, 19], "derived": [117], "cost": 62}, {"constraints": [177, 42, 19], "derived": [117], "cost": 62}, {"constraints": [-136, 81, 186], "derived": [-112], "cost": 62}, {"constraints": [177, 42, 19], "derived": [117], "cost": 62}, {"constraints": [177, 42, 19], "derived": [117], "cost": 62}, {"constraints": [-144, -143, -142, 174, -145], "derived": [141], "cost": 64}, {"constraints": [-144, -143, -142, 174, -145], "derived": [141], "cost": 64}, {"constraints": [-144, -143, -142, 174, -145], "derived": [141], "cost": 64}, {"constraints": [-144, -143, -142, 174, -145], "derived": [141], "cost": 64}, {"constraints": [163, 1695], "derived": [-98], "cost": 160}, {"constraints": [163, 1695], "derived": [-98], "cost": 160}, {"constraints": [153, 23], "derived": [-21, -25], "cost": 61}, {"constraints": [153, 23], "derived": [-21, -25], "cost": 61}, {"constraints": [72, 153, 178, 23], "derived": [-127, -147], "cost": 122}, {"constraints": [72, 153, 178, 23], "derived": [-127, -147], "cost": 122}, {"constraints": [72, 153, 178, 23], "derived": [-127, -147], "cost": 122}, {"constraints": [72, 153, 178, 23], "derived": [-127, -147], "cost": 122}, {"constraints": [48, 153, 175, 23], "derived": [-103], "cost": 122}, {"constraints": [72, 153, 178, 23], "derived": [-147], "cost": 122}, {"constraints": [151, 178, 23, 55], "derived": [-140], "cost": 122}, {"constraints": [137, 173], "derived": [-140], "cost": 61}, {"constraints": [163, 1695], "derived": [-98], "cost": 160}, {"constraints": [163, 1695], "derived": [-98], "cost": 160}, {"constraints": [163, 1695], "derived": [-98], "cost": 160}, {"constraints": [130, 173], "derived": [-128], "cost": 61}, {"constraints": [130, 134, 173, 137, 172, 141], "derived": [148], "cost": 124}, {"constraints": [130, 134, 173, 137, 172, 141], "derived": [148], "cost": 124}, {"constraints": [1, 19, 23, 7, 152, 153], "derived": [15], "cost": 124}, {"constraints": [130, 134, 173, 137, 172, 141], "derived": [148], "cost": 124}, {"constraints": [163, 1695], "derived": [-98], "cost": 160}, {"constraints": [163, 1695], "derived": [-98], "cost": 160}, {"constraints": [163, 1695], "derived": [-98], "cost": 160}, {"constraints": [163, 1695], "derived": [-98], "cost": 160}, {"constraints": [1695, 181, 157, 63], "derived": [-40], "cost": 221}, {"constraints": [1695, 181, 157, 63], "derived": [-40], "cost": 221}, {"constraints": [161, 1698, 155, 55], "derived": [-30], "cost": 221}, {"constraints": [35, 157], "derived": [-31, -34], "cost": 61}, {"constraints": [35, 155], "derived": [-30], "cost": 61}, {"constraints": [35, 155, 181, 55], "derived": [-100], "cost": 122}, {"constraints": [35, 155, 181, 55], "derived": [-100], "cost": 122}, {"constraints": [35, 155, 181, 55], "derived": [-100], "cost": 122}, {"constraints": [35, 155, 181, 55], "derived": [-100], "cost": 122}, {"constraints": [35, 155, 181, 55], "derived": [-100], "cost": 122}, {"constraints": [35, 155, 181, 55], "derived": [-100], "cost": 122}, {"constraints": [35, 155, 181, 55], "derived": [-100], "cost": 122}, {"constraints": [35, 164, 181, 59, 157], "derived": [99], "cost": 182}, {"constraints": [81, 99, 165, 87, 1690], "derived": [80, -78], "cost": 163}, {"constraints": [163, 93], "derived": [-78], "cost": 61}, {"constraints": [181, 93, 63], "derived": [39], "cost": 62}, {"constraints": [181, 93, 63], "derived": [39], "cost": 62}, {"constraints": [181, 93, 63], "derived": [39], "cost": 62}, {"constraints": [81, 99, 164, 165, 87, 93], "derived": [80], "cost": 124}, {"constraints": [81, 99, 164, 165, 87, 93], "derived": [80], "cost": 124}, {"constraints": [81, 99, 164, 165, 87, 93], "derived": [80], "cost": 124}, {"constraints": [81, 99, 164, 165, 87, 93], "derived": [80], "cost": 124}], "MUS-time": [11.78495979309082, 11.78420901298523, 11.43888235092163, 11.112540006637573, 11.075273990631104, 11.0042724609375, 10.835082530975342, 11.688349485397339, 11.672013282775879, 11.546765565872192, 11.413479089736938, 11.355567693710327, 11.310683965682983, 11.162362337112427, 11.10823369026184, 11.097254276275635, 10.911811828613281, 12.180620431900024, 11.973350048065186, 11.133497953414917, 11.085415840148926, 10.736945629119873, 10.340183734893799, 18.265055179595947, 17.960918426513672, 30.98414945602417, 27.593785285949707, 26.87694525718689, 25.507340669631958, 16.744011640548706, 18.29215168952942, 19.660603761672974, 18.37321162223816, 18.15506339073181, 24.016424655914307, 23.90377950668335, 23.241201877593994, 22.37727665901184, 14.76598072052002, 15.260366439819336, 8.097189903259277, 7.994543075561523, 7.751444101333618, 7.963442087173462, 7.389083623886108, 7.48167610168457, 7.284501552581787, 7.118483543395996, 7.056777715682983, 6.452085018157959, 6.294465065002441, 6.271632671356201, 6.187048435211182, 5.911101579666138, 6.3005805015563965, 5.770349025726318, 5.512975692749023, 5.387631893157959, 5.336295127868652, 5.230400323867798, 5.158242225646973, 5.0125274658203125, 4.937860727310181, 4.924546480178833, 4.876487970352173, 4.756254434585571, 4.7619309425354, 4.6153175830841064, 4.544580459594727, 4.463775634765625, 4.43066143989563, 4.2800164222717285, 3.6549623012542725, 3.5557773113250732, 3.4067907333374023, 3.297218084335327, 3.4007904529571533, 3.306090831756592, 3.179654598236084, 3.1031503677368164, 2.979086399078369, 2.9099533557891846, 2.8213069438934326, 2.739243268966675, 2.679659843444824, 2.576963424682617, 2.5031323432922363, 2.399414300918579, 2.315459966659546, 2.2544944286346436, 2.1951377391815186, 2.066549777984619, 2.0358269214630127, 1.931053638458252, 1.8633816242218018, 1.7900614738464355, 1.6978492736816406, 1.5493419170379639, 1.4327142238616943, 1.3697538375854492, 1.2684473991394043, 1.1998937129974365, 1.102726936340332, 1.035492181777954, 0.9675276279449463, 0.8714971542358398, 0.8030402660369873, 0.7012231349945068, 0.6278889179229736, 0.5617175102233887, 0.46755242347717285, 0.3956491947174072, 0.33586573600769043, 0.23499321937561035, 0.13708877563476562, 0.10004663467407227], "timeout": false}}