{"config": {"preseeding": true, "preseeding-minimal": false, "preseeding-grow": true, "preseeding-grow-maxsat": false, "sat-polarity": true, "postpone_opt": true, "postpone_opt_incr": false, "postpone_opt_greedy": true, "grow": true, "grow_sat": true, "grow_subset_maximal": false, "grow_maxsat": false, "timeout": 30, "instance": "simple", "output": "results/rq1_5/2020122112/20201221122149765932.json"}, "results": {"HS": [2, 2, 1], "HS_greedy": [4, 5, 0], "HS_incr": [0, 0, 0], "HS-opt-time": [0.0016689300537109375, 0.0013012886047363281, 0.000286102294921875], "HS-postpone-time": [0.00013709068298339844, 0.003198385238647461, 0], "SAT-time": [0.00013828277587890625, 0.0001742839813232422, 2.4318695068359375e-05], "grow-time": [5.4836273193359375e-06, 7.867813110351562e-06, 0], "#expl": 3, "expl_seq": [{"constraints": [4], "derived": [1]}, {"constraints": [1, 5, 6], "derived": [2]}, {"constraints": [2, 7], "derived": [-3]}], "OUS-time": [0.0025374889373779297, 0.0056149959564208984, 0.0004336833953857422], "timeout": false}}