{"config": {"preseeding": false, "sat-polarity": true, "sat-polarity-initial": false, "postpone_opt": true, "postpone_opt_incr": true, "postpone_opt_greedy": false, "grow": true, "grow_sat": false, "grow_subset_maximal": false, "grow_maxsat": true, "maxsat_polarities": true, "grow_maxsat_full_pos": false, "grow_maxsat_full_inv": false, "grow_maxsat_full_unif": true, "grow_maxsat_initial_pos": false, "grow_maxsat_initial_inv": false, "grow_maxsat_initial_unif": false, "grow_maxsat_actual_pos": false, "grow_maxsat_actual_unif": false, "grow_maxsat_actual_inv": false, "timeout": 7200, "instance": "p13", "output": "/data/brussel/101/vsc10143/OUSResults/experiment6_cous/2021011601/20210116013442950160.json"}, "results": {"HS": [0, 40, 0, 46, 0, 42, 0, 44, 0, 270], "HS_greedy": [0, 0, 0, 0, 0, 0, 0, 0, 0, 0], "HS_incr": [0, 1584, 0, 1673, 0, 1588, 0, 1311, 0, 5479], "HS-opt-time": [0, 59.830580949783325, 0, 86.28857398033142, 0, 48.721996545791626, 0, 39.063339710235596, 0, 4184.858489990234], "HS-postpone-time": [0, 0.12074947357177734, 0, 0.13293194770812988, 0, 0.12865781784057617, 0, 0.1042630672454834, 0, 0.4273223876953125], "SAT-time": [0, 6.8752806186676025, 0, 7.22172999382019, 0, 7.018015384674072, 0, 5.68742823600769, 0, 24.28518581390381], "grow-time": [0, 209.27197885513306, 0, 223.39112901687622, 0, 212.3042070865631, 0, 176.70719194412231, 0, 1878.2963988780975], "#expl": 4, "expl_seq": [{"constraints": [11943], "derived": [-10264, -10267], "cost": 100}, {"constraints": [11949], "derived": [10275], "cost": 100}, {"constraints": [10275, 10406], "derived": [-10278, -10277, -10276, -10274], "cost": 61}, {"constraints": [10275, 10404], "derived": [-10255, -10270, -10260, -10265], "cost": 61}], "OUS-time": [0, 278.9307622909546, 0, 320.00631308555603, 0, 271.01110434532166, 0, 223.8570306301117, 0, 0], "timeout": true}}