{"config": {"preseeding": true, "sat-polarity": true, "sat-polarity-initial": false, "postpone_opt": true, "postpone_opt_incr": true, "postpone_opt_greedy": true, "grow": true, "grow_sat": false, "grow_subset_maximal": false, "grow_maxsat": true, "maxsat_polarities": true, "grow_maxsat_full_pos": false, "grow_maxsat_full_inv": false, "grow_maxsat_full_unif": false, "grow_maxsat_initial_pos": false, "grow_maxsat_initial_inv": false, "grow_maxsat_initial_unif": false, "grow_maxsat_actual_pos": true, "grow_maxsat_actual_unif": false, "grow_maxsat_actual_inv": false, "timeout": 7200, "instance": "p20", "output": "/data/brussel/101/vsc10143/OUSResults/experiment6_cous/2021011613/20210116135202580961.json"}, "results": {"HS": [0, 2, 0, 3, 0, 2, 0, 1], "HS_greedy": [0, 21, 0, 6, 0, 63, 0, 8], "HS_incr": [0, 590, 0, 92, 0, 1424, 0, 141], "HS-opt-time": [0, 2.1381995677948, 0, 0.21190977096557617, 0, 8.185930013656616, 0, 0.0037255287170410156], "HS-postpone-time": [0, 0.21922039985656738, 0, 0.016508817672729492, 0, 1.5097789764404297, 0, 0.025922298431396484], "SAT-time": [0.286501407623291, 8.456492185592651, 0.3463001251220703, 1.2672462463378906, 0.34290504455566406, 18.002473831176758, 0.33736157417297363, 1.6806206703186035], "grow-time": [4.686498403549194, 150.13413095474243, 4.751903057098389, 45.84028935432434, 5.114736557006836, 6319.660095214844, 5.115017652511597, 441.0537190437317], "#expl": 3, "expl_seq": [{"constraints": [49310], "derived": [-47675], "cost": 100}, {"constraints": [49303], "derived": [-47623], "cost": 100}, {"constraints": [49311], "derived": [47679], "cost": 100}], "OUS-time": [0, 162.72502779960632, 0, 47.60054564476013, 0, 6351.451528787613, 0, 0], "timeout": true}}