{"config": {"preseeding": false, "sat-polarity": true, "sat-polarity-initial": false, "postpone_opt": true, "postpone_opt_incr": true, "postpone_opt_greedy": true, "grow": true, "grow_sat": false, "grow_subset_maximal": false, "grow_maxsat": true, "maxsat_polarities": true, "grow_maxsat_full_pos": false, "grow_maxsat_full_inv": false, "grow_maxsat_full_unif": false, "grow_maxsat_initial_pos": false, "grow_maxsat_initial_inv": false, "grow_maxsat_initial_unif": false, "grow_maxsat_actual_pos": true, "grow_maxsat_actual_unif": false, "grow_maxsat_actual_inv": false, "timeout": 7200, "instance": "p20", "output": "/data/brussel/101/vsc10143/OUSResults/experiment6_cous/2021011613/20210116135202579950.json"}, "results": {"HS": [0, 4, 0, 1], "HS_greedy": [0, 17, 0, 23], "HS_incr": [0, 197, 0, 356], "HS-opt-time": [0, 0.3979043960571289, 0, 0.0010602474212646484], "HS-postpone-time": [0, 0.05052328109741211, 0, 0.11786174774169922], "SAT-time": [0, 1.3853516578674316, 0, 2.5338797569274902], "grow-time": [0, 34.299752712249756, 0, 6935.609348058701], "#expl": 1, "expl_seq": [{"constraints": [30264], "derived": [-28629], "cost": 100}], "OUS-time": [0, 36.5692400932312, 0, 0], "timeout": true}}