{"config": {"preseeding": true, "preseeding-minimal": true, "sat-polarity": true, "postpone_opt": false, "postpone_opt_incr": false, "postpone_opt_greedy": false, "grow": true, "grow_subset_maximal": true, "grow_maxsat": false, "timeout": 3600, "instance": "simple"}, "results": {"HS": [3, 2, 1], "HS_greedy": [0, 0, 0], "HS_incr": [0, 0, 0], "HS-opt-time": [0.001026153564453125, 0.0006842613220214844, 0.0002913475036621094], "HS-postpone-time": [0, 0, 0], "SAT-time": [0.0001201629638671875, 0.00011301040649414062, 3.981590270996094e-05], "#expl": 3, "expl_seq": [{"constraints": [4], "derived": [1]}, {"constraints": [1, 5, 6], "derived": [2]}, {"constraints": [2, 7], "derived": [-3]}], "OUS-time": [0.001936197280883789, 0.0009946823120117188, 0.00038433074951171875], "timeout": false}}