{"config": {"instance": "p13", "timeout": 14400}, "results": {"#expl": 115, "expl_seq": [{"constraints": [1696], "derived": [22], "cost": 100}, {"constraints": [1696], "derived": [22], "cost": 100}, {"constraints": [153, 22], "derived": [-24, -23, -21, -25], "cost": 61}, {"constraints": [22, 151], "derived": [-7, -12, -2, -17], "cost": 61}, {"constraints": [178, 1687], "derived": [-86], "cost": 160}, {"constraints": [178, 1687], "derived": [-86], "cost": 160}, {"constraints": [1694, 159], "derived": [-67], "cost": 160}, {"constraints": [1688, 153], "derived": [-6], "cost": 160}, {"constraints": [1696, 181, 159], "derived": [-149], "cost": 220}, {"constraints": [1696, 155, 182], "derived": [-149], "cost": 220}, {"constraints": [1696, 155, 182], "derived": [-149], "cost": 220}, {"constraints": [1696, 155, 182], "derived": [-149], "cost": 220}, {"constraints": [1696, 155, 182], "derived": [-149], "cost": 220}, {"constraints": [1696, 155, 182], "derived": [-149], "cost": 220}, {"constraints": [1696, 155, 182], "derived": [-149], "cost": 220}, {"constraints": [1696, 155, 182], "derived": [-149], "cost": 220}, {"constraints": [1696, 155, 182], "derived": [-149], "cost": 220}, {"constraints": [1688, 163, 180], "derived": [-97, -57], "cost": 220}, {"constraints": [1688, 153, 159], "derived": [-57], "cost": 220}, {"constraints": [1688, 153, 159], "derived": [-57], "cost": 220}, {"constraints": [-103, 177, 157, 1694], "derived": [-43], "cost": 221}, {"constraints": [-103, 177, 157, 1694], "derived": [-43], "cost": 221}, {"constraints": [-134, 1694, 183], "derived": [44], "cost": 161}, {"constraints": [44, 157], "derived": [-45, -43, -42, -41], "cost": 61}, {"constraints": [177, -124, 44], "derived": [-20], "cost": 62}, {"constraints": [177, -124, 44], "derived": [-20], "cost": 62}, {"constraints": [-119, 177, 44], "derived": [-19], "cost": 62}, {"constraints": [-104, 177, 44], "derived": [-16], "cost": 62}, {"constraints": [-104, 177, 44], "derived": [-16], "cost": 62}, {"constraints": [-104, 177, 44], "derived": [-16], "cost": 62}, {"constraints": [177, -109, -124, -104, -119, 154, 44], "derived": [18, 114], "cost": 125}, {"constraints": [169, 114], "derived": [-112, -111, -115, -113], "cost": 61}, {"constraints": [1695, 177, -108, -115, -113], "derived": [120, 123], "cost": 163}, {"constraints": [1695, 177, -108, -115, -113], "derived": [120, 123], "cost": 163}, {"constraints": [18, 151], "derived": [-8, -13], "cost": 61}, {"constraints": [18, 180, 181, -86, 44], "derived": [-66, -129], "cost": 123}, {"constraints": [1695, 177, -108, -115, -113], "derived": [120, 123], "cost": 163}, {"constraints": [1695, 177, -108, -115, -113], "derived": [120, 123], "cost": 163}, {"constraints": [1695, 177, -108, -115, -113], "derived": [120, 123], "cost": 163}, {"constraints": [1695, 177, -108, -115, -113], "derived": [120, 123], "cost": 163}, {"constraints": [85, 165], "derived": [-83, -82, -81], "cost": 61}, {"constraints": [180, 85, 22, 165], "derived": [-72, -71, -73], "cost": 122}, {"constraints": [180, 85, 22, 165], "derived": [-71, -73], "cost": 122}, {"constraints": [180, 85, 22, 165], "derived": [-71, -73], "cost": 122}, {"constraints": [180, 85, 22, 165], "derived": [-71], "cost": 122}, {"constraints": [180, 85, 22, 165], "derived": [-71], "cost": 122}, {"constraints": [161, 75], "derived": [-71], "cost": 61}, {"constraints": [161, 75], "derived": [-71], "cost": 61}, {"constraints": [1695, 177, -108, -115, -113], "derived": [120, 123], "cost": 163}, {"constraints": [151, 15], "derived": [-5, -10], "cost": 61}, {"constraints": [177, -125, 15], "derived": [-40], "cost": 62}, {"constraints": [177, -125, 15], "derived": [-40], "cost": 62}, {"constraints": [18, 22, 151, 1688, 15], "derived": [9, -4], "cost": 163}, {"constraints": [161, 52], "derived": [-54, -53, -51], "cost": 61}, {"constraints": [18, 22, 151, 1688, 15], "derived": [9, -4], "cost": 163}, {"constraints": [1695, 177, -108, -115, -113], "derived": [120, 123], "cost": 163}, {"constraints": [1695, 177, -108, -115, -113], "derived": [120, 123], "cost": 163}, {"constraints": [1695, 177, -108, -115, -113], "derived": [120, 123], "cost": 163}, {"constraints": [1695, 177, -108, -115, -113], "derived": [120, 123], "cost": 163}, {"constraints": [1, 180, 52], "derived": [77], "cost": 62}, {"constraints": [1, 180, 52], "derived": [77], "cost": 62}, {"constraints": [1, 180, 52], "derived": [77], "cost": 62}, {"constraints": [1, 180, 52], "derived": [77], "cost": 62}, {"constraints": [1, 180, 52], "derived": [77], "cost": 62}, {"constraints": [77, 165], "derived": [-79, -78], "cost": 61}, {"constraints": [1695, 177, -108, 167], "derived": [-105], "cost": 221}, {"constraints": [-128, -143, -133, -148, 171, 174], "derived": [138, -140, -139, -137, -136], "cost": 124}, {"constraints": [138, 173], "derived": [-136, -140, -139, -137], "cost": 61}, {"constraints": [114, 185, -139, 169, 174], "derived": [-88], "cost": 182}, {"constraints": [114, 185, -139, 169, 174], "derived": [-88], "cost": 182}, {"constraints": [167, -149, 171, 77, 174, 114, -139, 185, -129], "derived": [-94, -145, 144, -142, -141, -99], "cost": 245}, {"constraints": [69, 159], "derived": [-64, -59], "cost": 61}, {"constraints": [151, 178, 69, 15], "derived": [-99], "cost": 122}, {"constraints": [151, 178, 69, 15], "derived": [-99], "cost": 122}, {"constraints": [151, 178, 69, 15], "derived": [-99], "cost": 122}, {"constraints": [151, 178, 69, 15], "derived": [-99], "cost": 122}, {"constraints": [144, 173], "derived": [-141], "cost": 61}, {"constraints": [151, 178, 69, 15], "derived": [-99], "cost": 122}, {"constraints": [89, 163], "derived": [-99], "cost": 61}, {"constraints": [9, 44, 175, 18, 22, 151, 157, 1695], "derived": [-118, -110], "cost": 284}, {"constraints": [157, 38], "derived": [-37, -36], "cost": 61}, {"constraints": [155, 38], "derived": [-33], "cost": 61}, {"constraints": [151, 9, 38, 175], "derived": [-118], "cost": 122}, {"constraints": [161, 63], "derived": [-61], "cost": 61}, {"constraints": [161, 63], "derived": [-61], "cost": 61}, {"constraints": [151, 9, 38, 175], "derived": [-118], "cost": 122}, {"constraints": [151, 9, 38, 175], "derived": [-118], "cost": 122}, {"constraints": [160, 161, 52, 69, 75, 63], "derived": [56], "cost": 124}, {"constraints": [160, 161, 52, 69, 75, 63], "derived": [56], "cost": 124}, {"constraints": [160, 161, 52, 69, 75, 63], "derived": [56], "cost": 124}, {"constraints": [160, 161, 52, 69, 75, 63], "derived": [56], "cost": 124}, {"constraints": [169, 123], "derived": [-121], "cost": 61}, {"constraints": [160, 161, 52, 69, 75, 63], "derived": [56], "cost": 124}, {"constraints": [169, 107], "derived": [-110, -106], "cost": 61}, {"constraints": [160, 161, 52, 69, 75, 63], "derived": [56], "cost": 124}, {"constraints": [160, 161, 52, 69, 75, 63], "derived": [56], "cost": 124}, {"constraints": [160, 161, 52, 69, 75, 63], "derived": [56], "cost": 124}, {"constraints": [160, 161, 52, 69, 75, 63], "derived": [56], "cost": 124}, {"constraints": [160, 161, 52, 69, 75, 63], "derived": [56], "cost": 124}, {"constraints": [160, 161, 52, 69, 75, 63], "derived": [56], "cost": 124}, {"constraints": [160, 161, 52, 69, 75, 63], "derived": [56], "cost": 124}, {"constraints": [160, 161, 52, 69, 75, 63], "derived": [56], "cost": 124}, {"constraints": [160, 161, 52, 69, 75, 63], "derived": [56], "cost": 124}, {"constraints": [1695, 22, 151, 9, 157, 47], "derived": [-31], "cost": 223}, {"constraints": [35, 157], "derived": [-31], "cost": 61}, {"constraints": [35, 157], "derived": [-31], "cost": 61}, {"constraints": [156, 35, 38, 44, 157, 47], "derived": [26], "cost": 124}, {"constraints": [156, 35, 38, 44, 157, 47], "derived": [26], "cost": 124}, {"constraints": [156, 35, 38, 44, 157, 47], "derived": [26], "cost": 124}, {"constraints": [130, 173], "derived": [-126], "cost": 61}, {"constraints": [144, 130, 147, 138, 172, 173], "derived": [131], "cost": 124}, {"constraints": [120, 169], "derived": [-116], "cost": 61}, {"constraints": [156, 35, 38, 44, 157, 47], "derived": [26], "cost": 124}, {"constraints": [156, 35, 38, 44, 157, 47], "derived": [26], "cost": 124}, {"constraints": [156, 35, 38, 44, 157, 47], "derived": [26], "cost": 124}], "MUS-time": [13.384865045547485, 12.422027587890625, 12.585972309112549, 12.294522285461426, 12.031484365463257, 12.482595443725586, 12.31237530708313, 12.229633808135986, 12.06556510925293, 11.45862364768982, 11.314388990402222, 10.96301794052124, 10.553537368774414, 14.695077419281006, 14.922923803329468, 14.926018476486206, 13.397362470626831, 40.924137115478516, 39.47798204421997, 22.103683948516846, 10.478055238723755, 12.95712947845459, 17.794100761413574, 9.279987335205078, 8.885727643966675, 8.656036138534546, 8.520270347595215, 8.449255228042603, 8.384056329727173, 8.606884002685547, 8.459156513214111, 8.34063458442688, 8.128155946731567, 7.989155530929565, 7.8078272342681885, 7.557368040084839, 7.483989715576172, 7.4298295974731445, 7.358577013015747, 7.568317174911499, 7.537387847900391, 8.265644311904907, 8.117614984512329, 7.2985124588012695, 8.721379518508911, 8.64310622215271, 7.379936218261719, 7.044733285903931, 7.086742401123047, 6.862670421600342, 6.774614334106445, 6.515167951583862, 6.640084743499756, 7.243800163269043, 6.9470977783203125, 6.633581876754761, 6.633722305297852, 6.510451793670654, 7.464293003082275, 6.912977933883667, 6.771965026855469, 5.511500358581543, 5.417744398117065, 5.1479172706604, 5.270361423492432, 4.864929914474487, 4.638091802597046, 4.391822099685669, 4.230353832244873, 4.168726444244385, 4.052243709564209, 3.922877311706543, 3.5436878204345703, 3.4096062183380127, 3.592411518096924, 3.433958053588867, 3.3339505195617676, 3.2329180240631104, 3.175889015197754, 3.1164536476135254, 2.8950130939483643, 2.758721351623535, 2.6967005729675293, 2.606276512145996, 2.5174827575683594, 2.4522385597229004, 2.3846726417541504, 2.2760229110717773, 2.190303325653076, 2.106304168701172, 2.0303945541381836, 2.072326898574829, 2.0042288303375244, 2.1824679374694824, 2.0749685764312744, 1.9427785873413086, 1.7776165008544922, 1.8161695003509521, 1.7265636920928955, 1.70794677734375, 1.7575535774230957, 1.3256943225860596, 1.2613260746002197, 1.203486680984497, 0.8505947589874268, 0.7844457626342773, 0.6972887516021729, 0.627758264541626, 0.5641858577728271, 0.45134949684143066, 0.39000892639160156, 0.3121027946472168, 0.22819113731384277, 0.16455578804016113, 0.06898355484008789], "timeout": false}}