{"config": {"preseeding": true, "preseeding-grow": true, "sat-polarity": true, "sat-polarity-initial": false, "postpone_opt": false, "postpone_opt_incr": false, "postpone_opt_greedy": false, "grow": true, "grow_sat": false, "grow_subset_maximal": false, "grow_maxsat": true, "grow_maxsat_neg_cost": false, "grow_maxsat_pos_cost": false, "grow_maxsat_max_cost_neg": false, "grow_maxsat_unit": true, "grow_maxsat_initial": false, "grow_maxsat_actual_pos": false, "grow_maxsat_actual_unif": false, "grow_maxsat_actual_inv": false, "timeout": 30, "instance": "origin-problem", "output": "results/20210107/20210107151536834629.json"}, "results": {"HS": [122, 61], "HS_greedy": [0, 0], "HS_incr": [0, 0], "HS-opt-time": [2.803746461868286, 13.357394695281982], "HS-postpone-time": [0, 0], "SAT-time": [0.12897610664367676, 0.07556271553039551], "grow-time": [8.714677095413208, 4.183065176010132], "#expl": 1, "expl_seq": [{"constraints": [1696], "derived": [-27]}], "OUS-time": [11.715720176696777, 0], "timeout": true}}